README
setup.py
pystates/__init__.py
pystates/pystates.py
pystates.egg-info/PKG-INFO
pystates.egg-info/SOURCES.txt
pystates.egg-info/dependency_links.txt
pystates.egg-info/top_level.txt
pystates/examples/__init__.py
pystates/examples/complex.py
pystates/examples/mymachine.py