Metadata-Version: 1.0
Name: pystates
Version: 0.8
Summary: A simple and powerful python state machine framework using coroutines
Home-page: http://wiki.github.com/egradman/pystates
Author: Eric Gradman
Author-email: eric@gradman.com
License: MIT
Platform: UNKNOWN
